modev/__init__.py
modev/approaches.py
modev/common.py
modev/default_pars.py
modev/etl.py
modev/evaluation.py
modev/execution.py
modev/exploration.py
modev/pipeline.py
modev/plotting.py
modev/selection.py
modev/utils.py
modev/validation.py
modev/data/example_labeled_data.csv
modev/templates/__init__.py
modev/templates/default.py
modev/templates/experiment_01.py
modev/templates/experiment_02.py
modev-0.2.1.dist-info/LICENSE.txt
modev-0.2.1.dist-info/METADATA
modev-0.2.1.dist-info/WHEEL
modev-0.2.1.dist-info/top_level.txt
modev-0.2.1.dist-info/RECORD
