Metadata-Version: 2.1
Name: modev
Version: 0.2.1
Summary: Model Development for Data Science Projects.
Home-page: https://github.com/pabloarosado/modev
Author: Pablo Rosado
Author-email: pabloarosado@gmail.com
License: UNKNOWN
Keywords: modev,Data Science,Machine Learning,Modeling
Platform: UNKNOWN
Classifier: Programming Language :: Python :: 3
Classifier: License :: OSI Approved :: MIT License
Classifier: Operating System :: OS Independent
Classifier: Topic :: Scientific/Engineering
Requires-Python: >=3.6
Requires-Dist: numpy
Requires-Dist: pandas
Requires-Dist: plotly
Requires-Dist: scikit-learn
Requires-Dist: tqdm
